broker_ql/__init__.py
broker_ql/connection.py
broker_ql/myclirc
broker_ql/myclirc_nt
broker_ql/results.py
broker_ql/server.py
broker_ql/session.py
broker_ql/util.py
broker_ql/version.py
broker_ql/entrypoints/__init__.py
broker_ql/entrypoints/main.py
broker_ql_plugin_tws/__init__.py
broker_ql_plugin_tws/data.py
broker_ql_plugin_tws/wrapper.py
BrokerQL-0.0.2.dist-info/LICENSE
BrokerQL-0.0.2.dist-info/METADATA
BrokerQL-0.0.2.dist-info/WHEEL
BrokerQL-0.0.2.dist-info/entry_points.txt
BrokerQL-0.0.2.dist-info/top_level.txt
BrokerQL-0.0.2.dist-info/RECORD
