Metadata-Version: 2.1
Name: BrokerQL
Version: 0.0.2
Summary: Use SQL to instantly query your online brokers (IBKR and more).
Home-page: https://brokerql.github.io
Author: Pan Jiabang
Author-email: panjiabang@gmail.com
License: AGPL v3
Project-URL: Documentation, https://brokerql.github.io
Project-URL: Source, https://github.com/BrokerQL/BrokerQL
Project-URL: Twitter, https://twitter.com/BrokerQL
Keywords: mysql sql tws brokers trading
Classifier: Development Status :: 4 - Beta
Classifier: Intended Audience :: Developers
Classifier: Intended Audience :: Financial and Insurance Industry
Classifier: Topic :: Office/Business :: Financial :: Investment
Classifier: License :: OSI Approved :: GNU Affero General Public License v3
Classifier: Programming Language :: Python :: 3.9
Classifier: Programming Language :: Python :: 3 :: Only
Requires-Python: >=3.9
License-File: LICENSE
Requires-Dist: ib-insync ==0.9.86
Requires-Dist: mycli ==1.27.0
Requires-Dist: mysql-mimic ==2.5.3
